bebe_conn/__init__.py
bebe_conn/agent.py
bebe_conn/cli.py
bebe_conn/core.py
bebe_conn/server.py
bebe_conn-1.0.2.dist-info/licenses/LICENSE
bebe_conn-1.0.2.dist-info/METADATA
bebe_conn-1.0.2.dist-info/WHEEL
bebe_conn-1.0.2.dist-info/entry_points.txt
bebe_conn-1.0.2.dist-info/top_level.txt
bebe_conn-1.0.2.dist-info/RECORD
