Metadata-Version: 2.4
Name: bebe-conn
Version: 1.0.2
Summary: Monitorizare laptop de la distanță cu interfață web și actualizări în timp real
Home-page: https://github.com/me-suzy/bebe-conn
Author: Ioan Fantanaru
Author-email: Ionel Balauta <ionel@example.com>
Maintainer-email: Ionel Balauta <ionel@example.com>
License: MIT
Project-URL: Homepage, https://github.com/ionel-balauta/bebe-conn
Project-URL: Documentation, https://github.com/ionel-balauta/bebe-conn#readme
Project-URL: Repository, https://github.com/ionel-balauta/bebe-conn.git
Project-URL: Bug Tracker, https://github.com/ionel-balauta/bebe-conn/issues
Keywords: monitoring,remote,laptop,web,dashboard,screenshots,system
Classifier: Development Status :: 4 - Beta
Classifier: Intended Audience :: End Users/Desktop
Classifier: License :: OSI Approved :: MIT License
Classifier: Operating System :: OS Independent
Classifier: Programming Language :: Python :: 3
Classifier: Programming Language :: Python :: 3.8
Classifier: Programming Language :: Python :: 3.9
Classifier: Programming Language :: Python :: 3.10
Classifier: Programming Language :: Python :: 3.11
Classifier: Programming Language :: Python :: 3.12
Classifier: Topic :: System :: Monitoring
Classifier: Topic :: System :: Networking
Classifier: Topic :: Internet :: WWW/HTTP :: Dynamic Content
Requires-Python: >=3.8
License-File: LICENSE
Requires-Dist: Flask>=2.3.0
Requires-Dist: requests>=2.31.0
Requires-Dist: psutil>=5.9.0
Requires-Dist: Pillow>=10.0.0
Requires-Dist: pyautogui>=0.9.50
Provides-Extra: dev
Requires-Dist: pytest>=7.0.0; extra == "dev"
Requires-Dist: pytest-cov>=4.0.0; extra == "dev"
Requires-Dist: black>=23.0.0; extra == "dev"
Requires-Dist: flake8>=6.0.0; extra == "dev"
Requires-Dist: mypy>=1.0.0; extra == "dev"
Dynamic: author
Dynamic: home-page
Dynamic: license-file
Dynamic: requires-python
